{"deviceId": "08BEAC028D14", "siteName": "\u7af9\u9ad8G\u623f", "gps_lon": 120.553, "gps_lat": 23.52, "startTime": "2024-08-20 10:00:00", "endTime": "2024-08-27 10:00:00", "timeScale": 1, "data": {"2024-08-20": {"0": {"pm2.5": [], "avgPm2.5": 0, "humidity": [], "avgHumidity": 0, "temperature": [], "avgTemperature": 0}, "1": {"pm2.5": [], "avgPm2.5": 0, "humidity": [], "avgHumidity": 0, "temperature": [], "avgTemperature": 0}, "2": {"pm2.5": [], "avgPm2.5": 0, "humidity": [], "avgHumidity": 0, "temperature": [], "avgTemperature": 0}, "3": {"pm2.5": [], "avgPm2.5": 0, "humidity": [], "avgHumidity": 0, "temperature": [], "avgTemperature": 0}, "4": {"pm2.5": [], "avgPm2.5": 0, "humidity": [], "avgHumidity": 0, "temperature": [], "avgTemperature": 0}, "5": {"pm2.5": [], "avgPm2.5": 0, "humidity": [], "avgHumidity": 0, "temperature": [], "avgTemperature": 0}, "6": {"pm2.5": [], "avgPm2.5": 0, "humidity": [], "avgHumidity": 0, "temperature": [], "avgTemperature": 0}, "7": {"pm2.5": [], "avgPm2.5": 0, "humidity": [], "avgHumidity": 0, "temperature": [], "avgTemperature": 0}, "8": {"pm2.5": [], "avgPm2.5": 0, "humidity": [], "avgHumidity": 0, "temperature": [], "avgTemperature": 0}, "9": {"pm2.5": [], "avgPm2.5": 0, "humidity": [], "avgHumidity": 0, "temperature": [], "avgTemperature": 0}, "10": {"pm2.5": [0.0], "avgPm2.5": 0.0, "humidity": [69.0], "avgHumidity": 69.0, "temperature": [22.75], "avgTemperature": 22.75}, "11": {"pm2.5": [0.0, 0.0, 0.0, 0.0, 0.0, 0.0, 0.0, 0.0, 0.0, 0.0], "avgPm2.5": 0.0, "humidity": [66.0, 64.0, 64.0, 68.0, 67.0, 65.0, 64.0, 63.0, 69.0, 66.0], "avgHumidity": 65.6, "temperature": [22.62, 22.62, 22.75, 22.75, 22.75, 22.75, 22.75, 22.75, 22.75, 22.75], "avgTemperature": 22.724}, "12": {"pm2.5": [0.0, 0.0, 0.0, 0.0, 0.0, 0.0, 0.0, 0.0, 0.0], "avgPm2.5": 0.0, "humidity": [64.0, 64.0, 63.0, 68.0, 64.0, 63.0, 68.0, 65.0, 64.0], "avgHumidity": 64.77777777777777, "temperature": [22.75, 22.75, 22.75, 22.75, 22.62, 22.62, 22.75, 22.62, 22.5], "avgTemperature": 22.678888888888892}, "13": {"pm2.5": [0.0, 0.0, 0.0, 0.0, 0.0, 0.0, 0.0, 0.0, 0.0], "avgPm2.5": 0.0, "humidity": [69.0, 66.0, 64.0, 63.0, 68.0, 66.0, 64.0, 63.0, 67.0], "avgHumidity": 65.55555555555556, "temperature": [22.75, 22.62, 22.62, 22.62, 22.87, 22.75, 22.75, 22.75, 22.87], "avgTemperature": 22.733333333333334}, "14": {"pm2.5": [0.0, 0.0, 0.0, 0.0, 0.0, 0.0, 0.0, 0.0, 0.0, 0.0], "avgPm2.5": 0.0, "humidity": [65.0, 64.0, 68.0, 66.0, 64.0, 64.0, 69.0, 67.0, 65.0, 64.0], "avgHumidity": 65.6, "temperature": [22.62, 22.62, 22.62, 22.75, 22.62, 22.62, 22.75, 22.75, 22.62, 22.62], "avgTemperature": 22.659}, "15": {"pm2.5": [0.0, 0.0, 0.0, 0.0, 0.0, 0.0, 0.0, 0.0, 0.0], "avgPm2.5": 0.0, "humidity": [67.0, 65.0, 64.0, 63.0, 68.0, 65.0, 68.0, 66.0, 65.0], "avgHumidity": 65.66666666666667, "temperature": [22.75, 22.5, 22.62, 22.62, 22.87, 22.75, 22.75, 22.75, 22.62], "avgTemperature": 22.692222222222224}, "16": {"pm2.5": [], "avgPm2.5": 0, "humidity": [], "avgHumidity": 0, "temperature": [], "avgTemperature": 0}, "17": {"pm2.5": [], "avgPm2.5": 0, "humidity": [], "avgHumidity": 0, "temperature": [], "avgTemperature": 0}, "18": {"pm2.5": [], "avgPm2.5": 0, "humidity": [], "avgHumidity": 0, "temperature": [], "avgTemperature": 0}, "19": {"pm2.5": [], "avgPm2.5": 0, "humidity": [], "avgHumidity": 0, "temperature": [], "avgTemperature": 0}, "20": {"pm2.5": [], "avgPm2.5": 0, "humidity": [], "avgHumidity": 0, "temperature": [], "avgTemperature": 0}, "21": {"pm2.5": [], "avgPm2.5": 0, "humidity": [], "avgHumidity": 0, "temperature": [], "avgTemperature": 0}, "22": {"pm2.5": [0.0, 0.0, 0.0, 0.0, 0.0, 0.0, 0.0, 0.0, 0.0, 0.0], "avgPm2.5": 0.0, "humidity": [66.0, 64.0, 63.0, 68.0, 65.0, 64.0, 68.0, 66.0, 64.0, 64.0], "avgHumidity": 65.2, "temperature": [22.62, 22.62, 22.62, 22.87, 22.62, 22.62, 22.62, 22.75, 22.5, 22.62], "avgTemperature": 22.646}, "23": {"pm2.5": [0.0, 0.0, 0.0, 0.0, 0.0, 0.0, 0.0, 0.0, 0.0, 0.0], "avgPm2.5": 0.0, "humidity": [68.0, 67.0, 64.0, 63.0, 68.0, 66.0, 64.0, 64.0, 66.0, 68.0], "avgHumidity": 65.8, "temperature": [22.62, 22.75, 22.62, 22.62, 22.75, 22.62, 22.62, 22.62, 22.62, 22.87], "avgTemperature": 22.671000000000003}}, "2024-08-21": {"0": {"pm2.5": [0.0, 0.0, 0.0, 0.0, 0.0, 0.0, 0.0, 0.0, 0.0, 0.0], "avgPm2.5": 0.0, "humidity": [65.0, 64.0, 63.0, 63.0, 63.0, 64.0, 64.0, 64.0, 65.0, 65.0], "avgHumidity": 64.0, "temperature": [22.87, 22.87, 22.87, 22.75, 22.75, 22.37, 22.12, 22.0, 22.0, 21.87], "avgTemperature": 22.447}, "1": {"pm2.5": [0.0, 0.0, 0.0, 0.0, 0.0, 0.0, 0.0, 0.0, 0.0], "avgPm2.5": 0.0, "humidity": [70.0, 67.0, 66.0, 66.0, 66.0, 66.0, 66.0, 66.0, 66.0], "avgHumidity": 66.55555555555556, "temperature": [22.37, 22.37, 22.25, 22.25, 22.12, 22.0, 22.0, 22.0, 22.0], "avgTemperature": 22.151111111111113}, "2": {"pm2.5": [0.0, 0.0, 0.0, 0.0, 0.0, 0.0, 0.0, 0.0, 0.0, 0.0], "avgPm2.5": 0.0, "humidity": [66.0, 66.0, 66.0, 71.0, 67.0, 67.0, 66.0, 66.0, 66.0, 66.0], "avgHumidity": 66.7, "temperature": [22.0, 21.87, 21.87, 22.37, 22.5, 22.25, 22.25, 22.12, 22.0, 22.0], "avgTemperature": 22.123}, "3": {"pm2.5": [0.0, 0.0, 0.0, 0.0, 0.0, 0.0, 0.0, 0.0, 0.0, 0.0], "avgPm2.5": 0.0, "humidity": [66.0, 66.0, 67.0, 67.0, 67.0, 66.0, 66.0, 67.0, 67.0, 67.0], "avgHumidity": 66.6, "temperature": [22.0, 22.0, 22.0, 22.0, 22.0, 22.0, 22.0, 22.0, 22.12, 22.0], "avgTemperature": 22.012}, "4": {"pm2.5": [0.0, 0.0, 0.0, 0.0, 0.0, 0.0, 0.0, 0.0, 0.0, 0.0], "avgPm2.5": 0.0, "humidity": [67.0, 67.0, 67.0, 67.0, 67.0, 68.0, 67.0, 67.0, 67.0, 67.0], "avgHumidity": 67.1, "temperature": [21.87, 22.0, 22.0, 22.0, 22.0, 22.0, 22.12, 22.12, 22.12, 22.12], "avgTemperature": 22.035000000000004}, "5": {"pm2.5": [0.0, 0.0, 0.0, 0.0, 0.0, 0.0, 0.0, 1.0], "avgPm2.5": 0.125, "humidity": [68.0, 67.0, 67.0, 67.0, 68.0, 68.0, 67.0, 67.0], "avgHumidity": 67.375, "temperature": [22.12, 22.12, 22.12, 22.12, 22.25, 22.25, 22.25, 22.25], "avgTemperature": 22.185000000000002}, "6": {"pm2.5": [], "avgPm2.5": 0, "humidity": [], "avgHumidity": 0, "temperature": [], "avgTemperature": 0}, "7": {"pm2.5": [], "avgPm2.5": 0, "humidity": [], "avgHumidity": 0, "temperature": [], "avgTemperature": 0}, "8": {"pm2.5": [0.0, 0.0, 0.0, 0.0, 0.0, 0.0, 0.0, 0.0, 0.0, 0.0], "avgPm2.5": 0.0, "humidity": [66.0, 65.0, 64.0, 63.0, 63.0, 63.0, 63.0, 63.0, 63.0, 63.0], "avgHumidity": 63.6, "temperature": [22.87, 22.87, 22.87, 22.75, 22.87, 22.75, 22.75, 22.75, 22.75, 22.75], "avgTemperature": 22.798000000000002}, "9": {"pm2.5": [0.0, 0.0, 0.0, 0.0, 0.0, 0.0, 0.0, 0.0, 0.0, 0.0], "avgPm2.5": 0.0, "humidity": [63.0, 68.0, 65.0, 64.0, 63.0, 63.0, 63.0, 63.0, 68.0, 66.0], "avgHumidity": 64.6, "temperature": [22.62, 22.87, 22.75, 22.87, 22.75, 22.75, 22.75, 22.62, 22.75, 22.75], "avgTemperature": 22.748}, "10": {"pm2.5": [0.0, 0.0, 0.0, 0.0, 0.0, 0.0, 0.0, 0.0, 0.0], "avgPm2.5": 0.0, "humidity": [65.0, 65.0, 64.0, 63.0, 63.0, 67.0, 65.0, 64.0, 63.0], "avgHumidity": 64.33333333333333, "temperature": [22.75, 22.75, 22.75, 22.75, 22.62, 22.75, 22.62, 22.75, 22.62], "avgTemperature": 22.706666666666667}, "11": {"pm2.5": [0.0, 0.0, 0.0, 0.0, 0.0, 0.0, 0.0, 0.0, 0.0, 0.0], "avgPm2.5": 0.0, "humidity": [63.0, 68.0, 65.0, 64.0, 63.0, 63.0, 69.0, 66.0, 64.0, 64.0], "avgHumidity": 64.9, "temperature": [22.62, 22.87, 22.62, 22.75, 22.75, 22.62, 22.75, 22.75, 22.75, 22.75], "avgTemperature": 22.723}, "12": {"pm2.5": [0.0, 0.0, 1.0, 0.0, 0.0, 0.0, 0.0, 0.0, 0.0, 0.0], "avgPm2.5": 0.1, "humidity": [64.0, 69.0, 66.0, 65.0, 64.0, 63.0, 69.0, 66.0, 65.0, 64.0], "avgHumidity": 65.5, "temperature": [22.62, 22.87, 22.75, 22.75, 22.75, 22.75, 22.87, 22.75, 22.75, 22.75], "avgTemperature": 22.761000000000003}, "13": {"pm2.5": [0.0, 0.0, 0.0, 0.0, 0.0, 0.0, 0.0, 0.0, 0.0, 0.0], "avgPm2.5": 0.0, "humidity": [66.0, 68.0, 65.0, 64.0, 63.0, 69.0, 67.0, 65.0, 67.0, 64.0], "avgHumidity": 65.8, "temperature": [22.62, 22.87, 22.62, 22.75, 22.75, 22.75, 22.87, 22.87, 22.25, 22.87], "avgTemperature": 22.722}, "14": {"pm2.5": [0.0, 0.0, 1.0, 0.0, 1.0, 0.0, 1.0, 0.0, 1.0, 0.0, 1.0, 0.0, 1.0, 0.0, 1.0, 0.0, 1.0, 0.0], "avgPm2.5": 0.4444444444444444, "humidity": [63.0, 68.0, 68.0, 66.0, 68.0, 65.0, 68.0, 63.0, 68.0, 63.0, 68.0, 69.0, 67.0, 66.0, 66.0, 64.0, 65.0, 64.0], "avgHumidity": 66.05555555555556, "temperature": [22.87, 22.87, 22.25, 22.87, 22.25, 22.87, 22.25, 22.87, 22.25, 22.75, 22.25, 22.75, 22.37, 22.75, 22.62, 22.75, 22.75, 22.75], "avgTemperature": 22.616111111111113}, "15": {"pm2.5": [1.0, 0.0, 1.0, 0.0, 0.0, 0.0, 0.0, 0.0, 0.0, 0.0, 0.0, 0.0, 0.0, 0.0, 0.0, 0.0, 0.0, 0.0], "avgPm2.5": 0.1111111111111111, "humidity": [64.0, 64.0, 64.0, 68.0, 64.0, 65.0, 63.0, 64.0, 63.0, 64.0, 63.0, 66.0, 63.0, 67.0, 63.0, 65.0, 63.0, 64.0], "avgHumidity": 64.27777777777777, "temperature": [22.75, 22.75, 22.87, 22.87, 22.75, 22.75, 22.75, 22.75, 22.75, 22.75, 22.75, 22.75, 22.75, 22.87, 22.75, 22.75, 22.75, 22.75], "avgTemperature": 22.77}, "16": {"pm2.5": [], "avgPm2.5": 0, "humidity": [], "avgHumidity": 0, "temperature": [], "avgTemperature": 0}, "17": {"pm2.5": [], "avgPm2.5": 0, "humidity": [], "avgHumidity": 0, "temperature": [], "avgTemperature": 0}, "18": {"pm2.5": [], "avgPm2.5": 0, "humidity": [], "avgHumidity": 0, "temperature": [], "avgTemperature": 0}, "19": {"pm2.5": [], "avgPm2.5": 0, "humidity": [], "avgHumidity": 0, "temperature": [], "avgTemperature": 0}, "20": {"pm2.5": [], "avgPm2.5": 0, "humidity": [], "avgHumidity": 0, "temperature": [], "avgTemperature": 0}, "21": {"pm2.5": [], "avgPm2.5": 0, "humidity": [], "avgHumidity": 0, "temperature": [], "avgTemperature": 0}, "22": {"pm2.5": [0.0, 0.0, 0.0, 0.0, 0.0, 0.0, 1.0, 0.0, 0.0, 0.0], "avgPm2.5": 0.1, "humidity": [69.0, 66.0, 64.0, 69.0, 66.0, 64.0, 69.0, 66.0, 65.0, 68.0], "avgHumidity": 66.6, "temperature": [22.62, 22.62, 22.5, 22.62, 22.62, 22.5, 22.75, 22.62, 22.5, 22.62], "avgTemperature": 22.597}, "23": {"pm2.5": [1.0, 1.0, 0.0, 1.0, 1.0, 1.0, 1.0, 0.0, 0.0, 0.0], "avgPm2.5": 0.6, "humidity": [67.0, 65.0, 65.0, 64.0, 69.0, 66.0, 64.0, 64.0, 64.0, 68.0], "avgHumidity": 65.6, "temperature": [22.75, 22.62, 22.62, 22.75, 22.87, 22.75, 22.75, 22.75, 22.62, 22.87], "avgTemperature": 22.735000000000003}}, "2024-08-22": {"0": {"pm2.5": [0.0, 0.0, 1.0, 1.0, 0.0, 0.0, 0.0, 0.0, 0.0], "avgPm2.5": 0.2222222222222222, "humidity": [66.0, 64.0, 66.0, 64.0, 62.0, 61.0, 60.0, 59.0, 59.0], "avgHumidity": 62.333333333333336, "temperature": [22.87, 22.87, 23.37, 24.0, 24.37, 24.75, 24.87, 24.87, 25.0], "avgTemperature": 24.10777777777778}, "1": {"pm2.5": [0.0, 0.0, 0.0, 0.0, 0.0, 0.0, 0.0, 0.0, 0.0], "avgPm2.5": 0.0, "humidity": [59.0, 58.0, 58.0, 58.0, 58.0, 58.0, 58.0, 58.0, 58.0], "avgHumidity": 58.111111111111114, "temperature": [25.0, 25.12, 25.12, 25.12, 25.12, 25.0, 25.0, 25.0, 25.0], "avgTemperature": 25.053333333333335}, "2": {"pm2.5": [0.0, 0.0, 1.0, 2.0, 2.0, 3.0, 3.0, 3.0, 3.0, 3.0], "avgPm2.5": 2.0, "humidity": [58.0, 58.0, 60.0, 61.0, 61.0, 61.0, 61.0, 61.0, 61.0, 61.0], "avgHumidity": 60.3, "temperature": [25.12, 25.25, 25.37, 25.5, 25.62, 25.75, 25.75, 25.87, 25.87, 25.87], "avgTemperature": 25.597}, "3": {"pm2.5": [2.0, 2.0, 2.0, 3.0, 4.0, 5.0, 5.0, 5.0, 3.0, 2.0], "avgPm2.5": 3.3, "humidity": [60.0, 60.0, 60.0, 61.0, 61.0, 61.0, 61.0, 61.0, 60.0, 59.0], "avgHumidity": 60.4, "temperature": [25.87, 25.75, 25.75, 25.87, 25.87, 25.87, 26.0, 26.0, 26.12, 26.0], "avgTemperature": 25.910000000000004}, "4": {"pm2.5": [3.0, 4.0, 4.0, 2.0, 2.0, 2.0, 4.0, 4.0, 5.0, 6.0], "avgPm2.5": 3.6, "humidity": [59.0, 59.0, 59.0, 58.0, 58.0, 59.0, 60.0, 60.0, 61.0, 61.0], "avgHumidity": 59.4, "temperature": [26.0, 26.12, 26.12, 26.0, 25.87, 25.87, 25.87, 25.87, 26.0, 26.12], "avgTemperature": 25.984}, "5": {"pm2.5": [6.0, 7.0, 6.0, 7.0, 7.0, 7.0, 7.0, 7.0, 7.0, 8.0], "avgPm2.5": 6.9, "humidity": [61.0, 61.0, 64.0, 64.0, 66.0, 67.0, 68.0, 69.0, 68.0, 69.0], "avgHumidity": 65.7, "temperature": [26.12, 26.12, 25.62, 24.75, 24.37, 24.12, 24.12, 24.12, 24.0, 23.87], "avgTemperature": 24.721}, "6": {"pm2.5": [7.0, 7.0, 8.0, 7.0, 8.0, 7.0, 7.0, 7.0, 7.0, 6.0], "avgPm2.5": 7.1, "humidity": [68.0, 69.0, 69.0, 70.0, 70.0, 70.0, 70.0, 70.0, 70.0, 70.0], "avgHumidity": 69.6, "temperature": [23.87, 23.87, 23.87, 23.87, 24.0, 24.0, 24.0, 24.12, 24.0, 24.12], "avgTemperature": 23.972}, "7": {"pm2.5": [7.0, 7.0, 6.0, 7.0, 6.0, 6.0, 6.0, 6.0, 6.0], "avgPm2.5": 6.333333333333333, "humidity": [70.0, 70.0, 70.0, 70.0, 70.0, 70.0, 70.0, 71.0, 72.0], "avgHumidity": 70.33333333333333, "temperature": [24.12, 24.12, 24.25, 24.25, 24.25, 24.25, 24.25, 24.25, 24.37], "avgTemperature": 24.234444444444446}, "8": {"pm2.5": [7.0, 7.0, 7.0, 6.0, 6.0, 7.0, 6.0, 6.0, 5.0, 5.0], "avgPm2.5": 6.2, "humidity": [72.0, 72.0, 72.0, 72.0, 71.0, 71.0, 72.0, 71.0, 71.0, 71.0], "avgHumidity": 71.5, "temperature": [24.37, 24.37, 24.37, 24.37, 24.37, 24.37, 24.37, 24.37, 24.25, 24.37], "avgTemperature": 24.358}, "9": {"pm2.5": [5.0, 5.0, 3.0, 2.0, 2.0, 1.0, 1.0, 1.0, 1.0, 1.0], "avgPm2.5": 2.2, "humidity": [71.0, 69.0, 68.0, 67.0, 67.0, 67.0, 67.0, 67.0, 67.0, 67.0], "avgHumidity": 67.7, "temperature": [24.37, 24.25, 24.0, 23.75, 23.5, 23.25, 23.12, 23.12, 23.0, 23.0], "avgTemperature": 23.536}, "10": {"pm2.5": [1.0, 1.0, 1.0, 1.0, 1.0, 1.0, 1.0, 0.0, 0.0, 1.0], "avgPm2.5": 0.8, "humidity": [67.0, 67.0, 66.0, 66.0, 66.0, 66.0, 66.0, 65.0, 65.0, 65.0], "avgHumidity": 65.9, "temperature": [22.87, 23.0, 23.0, 23.0, 23.0, 23.0, 23.0, 23.0, 22.87, 22.87], "avgTemperature": 22.961000000000002}, "11": {"pm2.5": [0.0, 1.0, 0.0, 0.0, 0.0, 0.0, 1.0, 0.0, 1.0, 0.0], "avgPm2.5": 0.3, "humidity": [65.0, 65.0, 65.0, 65.0, 65.0, 65.0, 65.0, 65.0, 65.0, 65.0], "avgHumidity": 65.0, "temperature": [22.87, 22.87, 22.87, 22.87, 22.75, 22.75, 22.75, 22.62, 22.62, 22.62], "avgTemperature": 22.759000000000004}, "12": {"pm2.5": [1.0, 0.0, 0.0, 0.0, 0.0, 1.0, 0.0, 1.0, 0.0, 0.0], "avgPm2.5": 0.3, "humidity": [65.0, 66.0, 65.0, 65.0, 65.0, 65.0, 65.0, 65.0, 65.0, 65.0], "avgHumidity": 65.1, "temperature": [22.62, 22.62, 22.62, 22.62, 22.62, 22.62, 22.5, 22.62, 22.62, 22.62], "avgTemperature": 22.608}, "13": {"pm2.5": [0.0, 0.0, 0.0, 0.0, 0.0, 0.0, 0.0, 0.0, 0.0], "avgPm2.5": 0.0, "humidity": [65.0, 66.0, 65.0, 65.0, 65.0, 65.0, 66.0, 65.0, 65.0], "avgHumidity": 65.22222222222223, "temperature": [22.5, 22.5, 22.5, 22.5, 22.5, 22.5, 22.5, 22.5, 22.5], "avgTemperature": 22.5}, "14": {"pm2.5": [0.0, 0.0, 0.0, 0.0, 0.0, 0.0, 0.0, 0.0, 0.0, 0.0], "avgPm2.5": 0.0, "humidity": [65.0, 65.0, 65.0, 65.0, 65.0, 65.0, 64.0, 65.0, 65.0, 65.0], "avgHumidity": 64.9, "temperature": [22.5, 22.37, 22.5, 22.37, 22.37, 22.37, 22.5, 22.37, 22.37, 22.37], "avgTemperature": 22.409000000000002}, "15": {"pm2.5": [0.0, 0.0, 0.0, 0.0, 0.0, 0.0, 0.0, 0.0, 0.0, 0.0], "avgPm2.5": 0.0, "humidity": [65.0, 65.0, 65.0, 65.0, 65.0, 65.0, 64.0, 65.0, 64.0, 64.0], "avgHumidity": 64.7, "temperature": [22.37, 22.25, 22.37, 22.37, 22.37, 22.37, 22.37, 22.37, 22.37, 22.37], "avgTemperature": 22.358000000000004}, "16": {"pm2.5": [], "avgPm2.5": 0, "humidity": [], "avgHumidity": 0, "temperature": [], "avgTemperature": 0}, "17": {"pm2.5": [], "avgPm2.5": 0, "humidity": [], "avgHumidity": 0, "temperature": [], "avgTemperature": 0}, "18": {"pm2.5": [], "avgPm2.5": 0, "humidity": [], "avgHumidity": 0, "temperature": [], "avgTemperature": 0}, "19": {"pm2.5": [], "avgPm2.5": 0, "humidity": [], "avgHumidity": 0, "temperature": [], "avgTemperature": 0}, "20": {"pm2.5": [], "avgPm2.5": 0, "humidity": [], "avgHumidity": 0, "temperature": [], "avgTemperature": 0}, "21": {"pm2.5": [], "avgPm2.5": 0, "humidity": [], "avgHumidity": 0, "temperature": [], "avgTemperature": 0}, "22": {"pm2.5": [0.0, 0.0, 0.0, 0.0, 0.0, 0.0, 0.0, 0.0, 0.0, 0.0], "avgPm2.5": 0.0, "humidity": [64.0, 68.0, 68.0, 66.0, 66.0, 64.0, 64.0, 67.0, 68.0, 66.0], "avgHumidity": 66.1, "temperature": [22.25, 22.25, 22.5, 22.37, 22.37, 22.37, 22.25, 22.25, 22.5, 22.37], "avgTemperature": 22.348000000000003}, "23": {"pm2.5": [0.0, 0.0, 0.0, 0.0, 0.0, 0.0, 0.0, 0.0, 0.0, 0.0], "avgPm2.5": 0.0, "humidity": [65.0, 65.0, 65.0, 64.0, 64.0, 70.0, 67.0, 66.0, 65.0, 65.0], "avgHumidity": 65.6, "temperature": [22.25, 22.25, 22.12, 22.25, 22.12, 22.5, 22.5, 22.5, 22.5, 22.5], "avgTemperature": 22.349}}, "2024-08-23": {"0": {"pm2.5": [0.0, 0.0, 0.0, 0.0, 0.0, 0.0, 0.0, 0.0, 0.0], "avgPm2.5": 0.0, "humidity": [65.0, 65.0, 64.0, 64.0, 64.0, 63.0, 63.0, 63.0, 63.0], "avgHumidity": 63.77777777777778, "temperature": [22.5, 22.5, 22.62, 22.87, 22.87, 23.0, 23.25, 23.25, 23.25], "avgTemperature": 22.901111111111113}, "1": {"pm2.5": [0.0, 1.0, 0.0, 1.0, 1.0, 1.0, 1.0, 1.0, 1.0, 1.0], "avgPm2.5": 0.8, "humidity": [64.0, 64.0, 64.0, 65.0, 64.0, 64.0, 63.0, 63.0, 64.0, 64.0], "avgHumidity": 63.9, "temperature": [23.0, 23.0, 22.87, 22.87, 22.87, 23.12, 23.37, 23.25, 23.12, 23.12], "avgTemperature": 23.059000000000005}, "2": {"pm2.5": [1.0, 1.0, 1.0, 1.0, 1.0, 1.0, 2.0, 2.0, 2.0, 2.0], "avgPm2.5": 1.4, "humidity": [64.0, 64.0, 65.0, 65.0, 65.0, 65.0, 65.0, 65.0, 65.0, 65.0], "avgHumidity": 64.8, "temperature": [23.0, 23.0, 23.0, 23.0, 23.0, 22.87, 22.87, 23.0, 22.87, 23.0], "avgTemperature": 22.961000000000002}, "3": {"pm2.5": [2.0, 2.0, 2.0, 2.0, 2.0, 2.0, 2.0, 2.0, 2.0, 2.0], "avgPm2.5": 2.0, "humidity": [65.0, 65.0, 65.0, 66.0, 65.0, 65.0, 65.0, 65.0, 66.0, 65.0], "avgHumidity": 65.2, "temperature": [22.87, 22.87, 23.0, 23.0, 23.0, 23.0, 23.0, 23.12, 23.12, 23.12], "avgTemperature": 23.01}, "4": {"pm2.5": [1.0, 2.0, 2.0, 3.0, 2.0, 3.0, 2.0, 2.0, 2.0, 3.0], "avgPm2.5": 2.2, "humidity": [65.0, 65.0, 65.0, 66.0, 65.0, 65.0, 65.0, 65.0, 66.0, 65.0], "avgHumidity": 65.2, "temperature": [23.12, 23.12, 23.12, 23.12, 23.0, 23.0, 23.0, 23.12, 23.12, 23.0], "avgTemperature": 23.072000000000003}, "5": {"pm2.5": [2.0, 2.0, 3.0, 2.0, 3.0, 2.0, 2.0, 2.0, 2.0, 2.0], "avgPm2.5": 2.2, "humidity": [65.0, 65.0, 65.0, 66.0, 65.0, 65.0, 66.0, 66.0, 66.0, 65.0], "avgHumidity": 65.4, "temperature": [23.0, 23.0, 23.0, 23.0, 23.0, 23.0, 23.0, 23.0, 23.12, 23.12], "avgTemperature": 23.024}, "6": {"pm2.5": [2.0, 2.0, 2.0, 3.0, 3.0, 2.0, 2.0, 2.0, 2.0, 2.0], "avgPm2.5": 2.2, "humidity": [65.0, 65.0, 65.0, 65.0, 65.0, 65.0, 66.0, 65.0, 66.0, 66.0], "avgHumidity": 65.3, "temperature": [23.12, 23.12, 23.12, 23.12, 23.12, 23.12, 23.12, 23.12, 23.12, 23.12], "avgTemperature": 23.12}, "7": {"pm2.5": [2.0, 2.0, 2.0, 2.0, 2.0, 2.0, 2.0, 2.0, 2.0], "avgPm2.5": 2.0, "humidity": [66.0, 66.0, 66.0, 65.0, 65.0, 65.0, 65.0, 65.0, 65.0], "avgHumidity": 65.33333333333333, "temperature": [23.25, 23.25, 23.25, 23.37, 23.25, 23.25, 23.37, 23.25, 23.37], "avgTemperature": 23.290000000000003}, "8": {"pm2.5": [2.0, 2.0, 2.0, 2.0, 2.0, 2.0, 2.0, 2.0, 2.0, 2.0], "avgPm2.5": 2.0, "humidity": [65.0, 65.0, 65.0, 65.0, 65.0, 65.0, 65.0, 65.0, 66.0, 65.0], "avgHumidity": 65.1, "temperature": [23.37, 23.37, 23.37, 23.37, 23.37, 23.37, 23.37, 23.37, 23.37, 23.37], "avgTemperature": 23.37}, "9": {"pm2.5": [2.0, 2.0, 2.0, 2.0, 2.0, 2.0, 2.0, 2.0, 2.0, 2.0], "avgPm2.5": 2.0, "humidity": [64.0, 65.0, 66.0, 67.0, 66.0, 66.0, 66.0, 66.0, 67.0, 66.0], "avgHumidity": 65.9, "temperature": [23.25, 23.12, 23.0, 22.87, 22.87, 22.75, 22.87, 22.75, 22.75, 22.62], "avgTemperature": 22.885}, "10": {"pm2.5": [2.0, 2.0, 2.0, 2.0, 2.0, 2.0, 2.0, 2.0, 2.0, 2.0], "avgPm2.5": 2.0, "humidity": [67.0, 67.0, 67.0, 67.0, 65.0, 65.0, 64.0, 64.0, 64.0, 64.0], "avgHumidity": 65.4, "temperature": [22.62, 22.62, 22.62, 22.87, 23.0, 23.12, 23.25, 23.25, 23.25, 23.25], "avgTemperature": 22.985}, "11": {"pm2.5": [2.0, 2.0, 2.0, 3.0, 2.0, 2.0, 2.0, 2.0, 2.0, 2.0], "avgPm2.5": 2.1, "humidity": [64.0, 64.0, 64.0, 64.0, 63.0, 63.0, 63.0, 63.0, 63.0, 63.0], "avgHumidity": 63.4, "temperature": [23.25, 23.25, 23.25, 23.25, 23.25, 23.12, 23.25, 23.12, 23.25, 23.25], "avgTemperature": 23.224}, "12": {"pm2.5": [2.0, 2.0, 2.0, 2.0, 2.0, 2.0, 2.0, 2.0, 2.0, 2.0], "avgPm2.5": 2.0, "humidity": [63.0, 63.0, 63.0, 63.0, 63.0, 63.0, 63.0, 63.0, 63.0, 63.0], "avgHumidity": 63.0, "temperature": [23.12, 23.12, 23.12, 23.12, 23.12, 23.12, 23.12, 23.12, 23.0, 23.0], "avgTemperature": 23.096}, "13": {"pm2.5": [2.0, 1.0, 2.0, 2.0, 2.0, 2.0, 1.0, 2.0, 2.0], "avgPm2.5": 1.7777777777777777, "humidity": [63.0, 63.0, 63.0, 63.0, 63.0, 63.0, 63.0, 63.0, 63.0], "avgHumidity": 63.0, "temperature": [23.0, 23.0, 23.0, 23.12, 23.0, 23.0, 23.12, 23.12, 23.12], "avgTemperature": 23.053333333333335}, "14": {"pm2.5": [2.0, 2.0, 2.0, 2.0, 2.0, 2.0, 2.0, 2.0, 2.0, 2.0], "avgPm2.5": 2.0, "humidity": [63.0, 63.0, 63.0, 63.0, 63.0, 63.0, 63.0, 63.0, 64.0, 63.0], "avgHumidity": 63.1, "temperature": [23.12, 23.0, 23.0, 23.0, 23.0, 23.0, 23.0, 22.87, 22.87, 22.87], "avgTemperature": 22.973000000000003}, "15": {"pm2.5": [2.0, 2.0, 2.0, 2.0, 2.0, 2.0, 1.0, 2.0, 2.0, 1.0], "avgPm2.5": 1.8, "humidity": [63.0, 63.0, 63.0, 63.0, 63.0, 63.0, 63.0, 63.0, 63.0, 62.0], "avgHumidity": 62.9, "temperature": [22.87, 22.87, 22.87, 23.0, 23.0, 23.0, 23.0, 23.0, 23.0, 22.87], "avgTemperature": 22.948}, "16": {"pm2.5": [], "avgPm2.5": 0, "humidity": [], "avgHumidity": 0, "temperature": [], "avgTemperature": 0}, "17": {"pm2.5": [], "avgPm2.5": 0, "humidity": [], "avgHumidity": 0, "temperature": [], "avgTemperature": 0}, "18": {"pm2.5": [], "avgPm2.5": 0, "humidity": [], "avgHumidity": 0, "temperature": [], "avgTemperature": 0}, "19": {"pm2.5": [], "avgPm2.5": 0, "humidity": [], "avgHumidity": 0, "temperature": [], "avgTemperature": 0}, "20": {"pm2.5": [], "avgPm2.5": 0, "humidity": [], "avgHumidity": 0, "temperature": [], "avgTemperature": 0}, "21": {"pm2.5": [], "avgPm2.5": 0, "humidity": [], "avgHumidity": 0, "temperature": [], "avgTemperature": 0}, "22": {"pm2.5": [1.0, 1.0, 1.0, 1.0, 1.0, 1.0, 1.0, 1.0, 1.0, 1.0], "avgPm2.5": 1.0, "humidity": [67.0, 64.0, 64.0, 62.0, 62.0, 62.0, 62.0, 68.0, 65.0, 63.0], "avgHumidity": 63.9, "temperature": [22.87, 22.87, 22.87, 22.87, 22.75, 22.75, 22.62, 22.75, 22.75, 22.75], "avgTemperature": 22.785000000000004}, "23": {"pm2.5": [1.0, 0.0, 1.0, 1.0, 1.0, 1.0, 1.0, 1.0, 0.0, 1.0], "avgPm2.5": 0.8, "humidity": [63.0, 63.0, 62.0, 62.0, 62.0, 62.0, 62.0, 62.0, 62.0, 62.0], "avgHumidity": 62.2, "temperature": [22.87, 22.75, 22.75, 22.75, 22.75, 22.75, 22.75, 22.75, 22.75, 22.75], "avgTemperature": 22.762}}, "2024-08-24": {"0": {"pm2.5": [1.0, 0.0, 0.0, 1.0, 1.0, 1.0, 1.0, 1.0], "avgPm2.5": 0.75, "humidity": [62.0, 62.0, 62.0, 62.0, 62.0, 62.0, 62.0, 62.0], "avgHumidity": 62.0, "temperature": [22.75, 22.87, 22.87, 22.87, 22.87, 22.87, 22.87, 22.87], "avgTemperature": 22.855000000000004}, "1": {"pm2.5": [1.0, 1.0, 1.0, 1.0, 1.0, 1.0, 1.0, 1.0, 2.0, 2.0], "avgPm2.5": 1.2, "humidity": [62.0, 62.0, 62.0, 63.0, 63.0, 65.0, 64.0, 65.0, 64.0, 63.0], "avgHumidity": 63.3, "temperature": [22.87, 23.0, 22.87, 22.87, 22.5, 22.25, 22.25, 22.37, 22.62, 22.75], "avgTemperature": 22.635}, "2": {"pm2.5": [2.0, 2.0, 1.0, 2.0, 1.0, 1.0, 2.0, 2.0, 2.0, 2.0], "avgPm2.5": 1.7, "humidity": [63.0, 63.0, 63.0, 64.0, 65.0, 66.0, 65.0, 66.0, 66.0, 66.0], "avgHumidity": 64.7, "temperature": [22.87, 23.0, 22.87, 22.5, 22.37, 22.25, 22.25, 22.12, 22.12, 22.12], "avgTemperature": 22.447000000000003}, "3": {"pm2.5": [2.0, 2.0, 1.0, 2.0, 2.0, 1.0, 2.0, 2.0, 2.0], "avgPm2.5": 1.7777777777777777, "humidity": [66.0, 66.0, 66.0, 66.0, 66.0, 67.0, 66.0, 66.0, 66.0], "avgHumidity": 66.11111111111111, "temperature": [22.12, 22.12, 22.12, 22.12, 22.12, 22.12, 22.12, 22.25, 22.25], "avgTemperature": 22.14888888888889}, "4": {"pm2.5": [3.0, 3.0, 2.0, 2.0, 2.0, 2.0, 2.0, 2.0, 2.0, 2.0], "avgPm2.5": 2.2, "humidity": [67.0, 66.0, 66.0, 66.0, 66.0, 66.0, 66.0, 66.0, 66.0, 66.0], "avgHumidity": 66.1, "temperature": [22.25, 22.25, 22.25, 22.25, 22.25, 22.25, 22.25, 22.25, 22.12, 22.12], "avgTemperature": 22.224}, "5": {"pm2.5": [2.0, 2.0, 2.0, 2.0, 3.0, 3.0, 3.0, 3.0, 3.0, 3.0], "avgPm2.5": 2.6, "humidity": [67.0, 66.0, 66.0, 66.0, 67.0, 67.0, 67.0, 67.0, 67.0, 67.0], "avgHumidity": 66.7, "temperature": [22.25, 22.25, 22.12, 22.12, 22.25, 22.25, 22.37, 22.37, 22.37, 22.37], "avgTemperature": 22.272000000000002}, "6": {"pm2.5": [3.0, 3.0, 2.0, 2.0, 2.0, 2.0, 2.0, 2.0, 1.0], "avgPm2.5": 2.111111111111111, "humidity": [67.0, 67.0, 66.0, 65.0, 64.0, 64.0, 64.0, 64.0, 64.0], "avgHumidity": 65.0, "temperature": [22.37, 22.25, 22.62, 22.75, 22.87, 22.87, 22.87, 22.87, 22.87], "avgTemperature": 22.704444444444448}, "7": {"pm2.5": [1.0, 1.0, 1.0, 1.0, 1.0, 1.0, 1.0, 1.0, 1.0], "avgPm2.5": 1.0, "humidity": [63.0, 62.0, 62.0, 62.0, 62.0, 62.0, 68.0, 65.0, 64.0], "avgHumidity": 63.333333333333336, "temperature": [22.87, 22.75, 22.87, 22.75, 22.75, 22.75, 22.87, 22.87, 23.0], "avgTemperature": 22.831111111111113}, "8": {"pm2.5": [1.0, 1.0, 1.0, 1.0, 1.0, 1.0, 1.0, 1.0, 1.0, 1.0], "avgPm2.5": 1.0, "humidity": [63.0, 62.0, 62.0, 62.0, 63.0, 67.0, 65.0, 64.0, 63.0, 63.0], "avgHumidity": 63.4, "temperature": [22.87, 22.87, 22.75, 22.75, 22.75, 22.87, 22.87, 22.87, 22.87, 22.75], "avgTemperature": 22.822000000000003}, "9": {"pm2.5": [1.0, 1.0, 1.0, 1.0, 0.0, 1.0, 1.0, 0.0, 1.0, 0.0], "avgPm2.5": 0.7, "humidity": [62.0, 65.0, 67.0, 64.0, 64.0, 63.0, 62.0, 62.0, 68.0, 65.0], "avgHumidity": 64.2, "temperature": [22.75, 22.75, 22.87, 22.75, 22.87, 22.87, 22.87, 22.62, 22.87, 22.75], "avgTemperature": 22.797000000000004}, "10": {"pm2.5": [1.0, 1.0, 1.0, 1.0, 1.0, 1.0, 1.0, 0.0, 0.0, 0.0], "avgPm2.5": 0.7, "humidity": [64.0, 63.0, 63.0, 64.0, 63.0, 68.0, 66.0, 64.0, 64.0, 63.0], "avgHumidity": 64.2, "temperature": [22.87, 22.87, 22.75, 22.75, 22.87, 22.75, 22.87, 22.75, 22.75, 22.75], "avgTemperature": 22.798000000000002}, "11": {"pm2.5": [0.0, 1.0, 0.0, 0.0, 0.0, 0.0, 0.0, 0.0, 0.0, 0.0], "avgPm2.5": 0.1, "humidity": [69.0, 66.0, 64.0, 63.0, 62.0, 66.0, 67.0, 64.0, 64.0, 62.0], "avgHumidity": 64.7, "temperature": [22.87, 22.87, 22.87, 22.87, 22.75, 22.75, 22.87, 22.87, 22.87, 22.75], "avgTemperature": 22.834000000000003}, "12": {"pm2.5": [0.0, 0.0, 0.0, 0.0, 0.0, 0.0, 0.0, 0.0, 0.0, 0.0], "avgPm2.5": 0.0, "humidity": [67.0, 66.0, 64.0, 64.0, 62.0, 68.0, 66.0, 64.0, 64.0, 66.0], "avgHumidity": 65.1, "temperature": [22.75, 22.87, 22.75, 22.87, 22.75, 22.75, 22.75, 22.75, 22.75, 22.75], "avgTemperature": 22.774}, "13": {"pm2.5": [0.0, 0.0, 0.0, 0.0, 0.0, 0.0, 0.0, 0.0, 0.0], "avgPm2.5": 0.0, "humidity": [67.0, 64.0, 63.0, 63.0, 67.0, 66.0, 64.0, 63.0, 63.0], "avgHumidity": 64.44444444444444, "temperature": [22.87, 22.75, 22.75, 22.75, 22.75, 22.75, 22.75, 22.75, 22.75], "avgTemperature": 22.763333333333335}, "14": {"pm2.5": [0.0, 0.0, 0.0, 0.0, 0.0, 0.0, 0.0, 0.0, 0.0, 0.0], "avgPm2.5": 0.0, "humidity": [67.0, 66.0, 64.0, 63.0, 63.0, 68.0, 66.0, 64.0, 63.0, 67.0], "avgHumidity": 65.1, "temperature": [22.75, 22.75, 22.75, 22.75, 22.87, 22.87, 22.75, 22.75, 22.75, 22.87], "avgTemperature": 22.786}, "15": {"pm2.5": [0.0, 0.0, 0.0, 0.0, 0.0, 0.0, 0.0, 0.0, 0.0, 0.0], "avgPm2.5": 0.0, "humidity": [65.0, 64.0, 63.0, 68.0, 65.0, 63.0, 62.0, 68.0, 65.0, 63.0], "avgHumidity": 64.6, "temperature": [22.75, 22.75, 22.75, 22.87, 22.75, 22.87, 22.87, 22.87, 22.87, 22.87], "avgTemperature": 22.822000000000003}, "16": {"pm2.5": [], "avgPm2.5": 0, "humidity": [], "avgHumidity": 0, "temperature": [], "avgTemperature": 0}, "17": {"pm2.5": [], "avgPm2.5": 0, "humidity": [], "avgHumidity": 0, "temperature": [], "avgTemperature": 0}, "18": {"pm2.5": [], "avgPm2.5": 0, "humidity": [], "avgHumidity": 0, "temperature": [], "avgTemperature": 0}, "19": {"pm2.5": [], "avgPm2.5": 0, "humidity": [], "avgHumidity": 0, "temperature": [], "avgTemperature": 0}, "20": {"pm2.5": [], "avgPm2.5": 0, "humidity": [], "avgHumidity": 0, "temperature": [], "avgTemperature": 0}, "21": {"pm2.5": [], "avgPm2.5": 0, "humidity": [], "avgHumidity": 0, "temperature": [], "avgTemperature": 0}, "22": {"pm2.5": [0.0, 0.0, 0.0, 0.0, 0.0, 0.0, 0.0, 0.0, 0.0, 0.0], "avgPm2.5": 0.0, "humidity": [68.0, 65.0, 64.0, 68.0, 65.0, 63.0, 63.0, 67.0, 65.0, 63.0], "avgHumidity": 65.1, "temperature": [22.87, 22.62, 22.75, 22.87, 22.75, 22.75, 22.75, 22.87, 22.75, 22.75], "avgTemperature": 22.773000000000003}, "23": {"pm2.5": [0.0, 0.0, 0.0, 0.0, 0.0, 0.0, 0.0, 0.0, 0.0, 0.0], "avgPm2.5": 0.0, "humidity": [67.0, 65.0, 64.0, 69.0, 66.0, 64.0, 64.0, 64.0, 68.0, 65.0], "avgHumidity": 65.6, "temperature": [22.62, 22.62, 22.62, 22.62, 22.75, 22.75, 22.75, 22.75, 22.87, 22.87], "avgTemperature": 22.722}}, "2024-08-25": {"0": {"pm2.5": [0.0, 0.0, 0.0, 0.0, 0.0, 0.0, 0.0, 0.0, 0.0], "avgPm2.5": 0.0, "humidity": [63.0, 63.0, 62.0, 62.0, 67.0, 65.0, 64.0, 63.0, 63.0], "avgHumidity": 63.55555555555556, "temperature": [23.0, 22.87, 22.87, 22.87, 23.0, 23.0, 23.0, 23.12, 23.0], "avgTemperature": 22.970000000000002}, "1": {"pm2.5": [1.0, 1.0, 1.0, 1.0, 1.0, 1.0, 1.0, 1.0, 1.0, 1.0], "avgPm2.5": 1.0, "humidity": [63.0, 62.0, 62.0, 62.0, 62.0, 62.0, 64.0, 67.0, 65.0, 64.0], "avgHumidity": 63.3, "temperature": [23.0, 23.0, 22.87, 22.87, 22.87, 22.87, 22.87, 23.0, 22.87, 22.87], "avgTemperature": 22.909000000000002}, "2": {"pm2.5": [1.0, 1.0, 1.0, 1.0, 1.0, 1.0, 1.0, 2.0, 2.0, 2.0], "avgPm2.5": 1.3, "humidity": [63.0, 63.0, 63.0, 63.0, 63.0, 63.0, 63.0, 63.0, 63.0, 64.0], "avgHumidity": 63.1, "temperature": [23.0, 22.87, 22.87, 22.87, 22.87, 22.87, 22.87, 22.87, 22.87, 22.87], "avgTemperature": 22.883000000000003}, "3": {"pm2.5": [2.0, 2.0, 1.0, 1.0, 1.0, 2.0, 2.0, 2.0, 1.0, 1.0], "avgPm2.5": 1.5, "humidity": [63.0, 63.0, 62.0, 62.0, 63.0, 63.0, 63.0, 62.0, 63.0, 64.0], "avgHumidity": 62.8, "temperature": [22.87, 22.87, 22.87, 22.87, 22.87, 23.0, 23.12, 23.0, 22.75, 22.5], "avgTemperature": 22.872000000000003}, "4": {"pm2.5": [1.0, 1.0, 2.0, 2.0, 1.0, 2.0, 1.0, 1.0, 1.0, 2.0], "avgPm2.5": 1.4, "humidity": [64.0, 65.0, 65.0, 65.0, 65.0, 65.0, 65.0, 65.0, 66.0, 66.0], "avgHumidity": 65.1, "temperature": [22.25, 22.12, 22.25, 22.25, 22.25, 22.12, 22.12, 22.12, 22.12, 22.12], "avgTemperature": 22.172000000000004}, "5": {"pm2.5": [2.0, 2.0, 2.0, 1.0, 2.0, 3.0, 3.0, 4.0, 5.0, 5.0], "avgPm2.5": 2.9, "humidity": [66.0, 66.0, 66.0, 66.0, 66.0, 67.0, 67.0, 67.0, 67.0, 67.0], "avgHumidity": 66.5, "temperature": [22.25, 22.12, 22.25, 22.12, 22.25, 22.25, 22.37, 22.37, 22.37, 22.37], "avgTemperature": 22.272000000000002}, "6": {"pm2.5": [6.0, 6.0, 5.0, 5.0, 4.0, 4.0, 6.0, 6.0, 7.0], "avgPm2.5": 5.444444444444445, "humidity": [67.0, 67.0, 66.0, 66.0, 66.0, 67.0, 68.0, 67.0, 68.0], "avgHumidity": 66.88888888888889, "temperature": [22.37, 22.5, 22.37, 22.25, 22.25, 22.25, 22.37, 22.37, 22.37], "avgTemperature": 22.34444444444445}, "7": {"pm2.5": [9.0, 8.0, 7.0, 6.0, 4.0, 5.0, 4.0, 5.0, 5.0, 6.0], "avgPm2.5": 5.9, "humidity": [67.0, 67.0, 65.0, 64.0, 64.0, 63.0, 63.0, 64.0, 64.0, 64.0], "avgHumidity": 64.5, "temperature": [22.62, 23.0, 23.12, 23.12, 23.12, 23.12, 23.25, 23.25, 23.25, 23.25], "avgTemperature": 23.110000000000003}, "8": {"pm2.5": [6.0, 6.0, 6.0, 7.0, 7.0, 8.0, 7.0, 7.0, 6.0, 5.0], "avgPm2.5": 6.5, "humidity": [64.0, 63.0, 64.0, 64.0, 65.0, 64.0, 64.0, 64.0, 63.0, 63.0], "avgHumidity": 63.8, "temperature": [23.25, 23.25, 23.25, 23.37, 23.37, 23.37, 23.37, 23.25, 23.25, 23.12], "avgTemperature": 23.285000000000004}, "9": {"pm2.5": [4.0, 4.0, 3.0, 3.0, 3.0, 2.0, 2.0, 2.0, 2.0, 2.0], "avgPm2.5": 2.7, "humidity": [63.0, 63.0, 62.0, 62.0, 63.0, 62.0, 62.0, 62.0, 62.0, 63.0], "avgHumidity": 62.4, "temperature": [23.0, 23.0, 22.87, 22.87, 22.87, 22.87, 22.87, 22.87, 22.87, 22.87], "avgTemperature": 22.896000000000004}, "10": {"pm2.5": [2.0, 2.0, 2.0, 2.0, 2.0, 2.0, 2.0, 2.0, 2.0, 2.0], "avgPm2.5": 2.0, "humidity": [62.0, 63.0, 63.0, 63.0, 63.0, 62.0, 63.0, 65.0, 67.0, 65.0], "avgHumidity": 63.6, "temperature": [22.75, 22.75, 22.75, 22.75, 22.75, 22.75, 22.62, 22.75, 22.87, 22.75], "avgTemperature": 22.749000000000002}, "11": {"pm2.5": [2.0, 2.0, 2.0, 2.0, 2.0, 2.0, 2.0, 2.0, 2.0, 2.0], "avgPm2.5": 2.0, "humidity": [64.0, 63.0, 63.0, 63.0, 63.0, 68.0, 66.0, 64.0, 64.0, 63.0], "avgHumidity": 64.1, "temperature": [22.87, 22.87, 22.75, 22.87, 22.75, 22.75, 22.87, 22.87, 22.87, 22.75], "avgTemperature": 22.822000000000003}, "12": {"pm2.5": [2.0, 2.0, 2.0, 2.0, 2.0, 2.0, 2.0, 2.0, 2.0, 2.0], "avgPm2.5": 2.0, "humidity": [63.0, 62.0, 68.0, 66.0, 64.0, 64.0, 63.0, 63.0, 63.0, 68.0], "avgHumidity": 64.4, "temperature": [22.75, 22.75, 22.87, 22.87, 22.87, 22.87, 22.87, 22.75, 22.75, 22.87], "avgTemperature": 22.822000000000003}, "13": {"pm2.5": [2.0, 2.0, 2.0, 2.0, 2.0, 2.0, 2.0, 2.0, 2.0], "avgPm2.5": 2.0, "humidity": [66.0, 64.0, 63.0, 63.0, 63.0, 63.0, 68.0, 66.0, 64.0], "avgHumidity": 64.44444444444444, "temperature": [22.87, 22.87, 22.87, 22.87, 22.87, 22.75, 22.87, 22.87, 22.87], "avgTemperature": 22.85666666666667}, "14": {"pm2.5": [2.0, 2.0, 2.0, 2.0, 2.0, 2.0, 2.0, 1.0, 2.0, 2.0], "avgPm2.5": 1.9, "humidity": [63.0, 63.0, 65.0, 67.0, 65.0, 64.0, 63.0, 63.0, 63.0, 62.0], "avgHumidity": 63.8, "temperature": [22.87, 22.75, 22.75, 22.87, 22.75, 22.87, 22.87, 22.75, 22.75, 22.87], "avgTemperature": 22.810000000000002}, "15": {"pm2.5": [2.0, 2.0, 2.0, 2.0, 2.0, 2.0, 2.0, 2.0, 2.0, 2.0], "avgPm2.5": 2.0, "humidity": [68.0, 66.0, 64.0, 64.0, 63.0, 62.0, 62.0, 62.0, 67.0, 65.0], "avgHumidity": 64.3, "temperature": [22.87, 22.87, 22.87, 23.0, 23.0, 22.87, 22.87, 22.87, 23.0, 22.87], "avgTemperature": 22.909}, "16": {"pm2.5": [], "avgPm2.5": 0, "humidity": [], "avgHumidity": 0, "temperature": [], "avgTemperature": 0}, "17": {"pm2.5": [], "avgPm2.5": 0, "humidity": [], "avgHumidity": 0, "temperature": [], "avgTemperature": 0}, "18": {"pm2.5": [], "avgPm2.5": 0, "humidity": [], "avgHumidity": 0, "temperature": [], "avgTemperature": 0}, "19": {"pm2.5": [], "avgPm2.5": 0, "humidity": [], "avgHumidity": 0, "temperature": [], "avgTemperature": 0}, "20": {"pm2.5": [], "avgPm2.5": 0, "humidity": [], "avgHumidity": 0, "temperature": [], "avgTemperature": 0}, "21": {"pm2.5": [], "avgPm2.5": 0, "humidity": [], "avgHumidity": 0, "temperature": [], "avgTemperature": 0}, "22": {"pm2.5": [1.0, 1.0, 1.0, 0.0, 1.0, 1.0, 1.0, 1.0, 1.0, 0.0], "avgPm2.5": 0.8, "humidity": [68.0, 65.0, 63.0, 63.0, 62.0, 67.0, 64.0, 63.0, 63.0, 63.0], "avgHumidity": 64.1, "temperature": [22.87, 22.87, 22.87, 22.87, 22.87, 23.0, 22.87, 22.87, 22.87, 22.75], "avgTemperature": 22.871000000000002}, "23": {"pm2.5": [1.0, 1.0, 1.0, 0.0, 0.0, 0.0, 0.0, 1.0, 1.0, 1.0], "avgPm2.5": 0.6, "humidity": [67.0, 64.0, 63.0, 62.0, 65.0, 67.0, 64.0, 63.0, 63.0, 63.0], "avgHumidity": 64.1, "temperature": [23.0, 22.87, 22.87, 22.87, 22.75, 22.87, 22.87, 22.87, 23.0, 23.0], "avgTemperature": 22.897000000000002}}, "2024-08-26": {"0": {"pm2.5": [1.0, 1.0, 2.0, 3.0, 2.0, 2.0, 2.0, 2.0, 3.0], "avgPm2.5": 2.0, "humidity": [63.0, 65.0, 66.0, 66.0, 66.0, 66.0, 65.0, 65.0, 63.0], "avgHumidity": 65.0, "temperature": [23.0, 23.0, 23.25, 23.62, 23.62, 23.75, 23.75, 23.87, 23.87], "avgTemperature": 23.525555555555556}, "1": {"pm2.5": [3.0, 2.0, 2.0, 2.0, 3.0, 3.0, 3.0, 2.0, 2.0, 2.0], "avgPm2.5": 2.4, "humidity": [63.0, 63.0, 62.0, 62.0, 62.0, 62.0, 62.0, 62.0, 62.0, 61.0], "avgHumidity": 62.1, "temperature": [23.87, 23.87, 23.87, 23.87, 23.75, 23.87, 23.75, 23.62, 23.62, 23.62], "avgTemperature": 23.771}, "2": {"pm2.5": [1.0, 1.0, 2.0, 2.0, 2.0, 2.0, 2.0, 2.0, 2.0], "avgPm2.5": 1.7777777777777777, "humidity": [61.0, 61.0, 61.0, 61.0, 61.0, 61.0, 61.0, 61.0, 64.0], "avgHumidity": 61.333333333333336, "temperature": [23.62, 23.62, 23.62, 23.62, 23.62, 23.5, 23.5, 23.5, 23.12], "avgTemperature": 23.52444444444445}, "3": {"pm2.5": [2.0, 2.0, 3.0, 3.0, 2.0, 2.0, 3.0, 3.0, 3.0, 2.0], "avgPm2.5": 2.5, "humidity": [65.0, 64.0, 64.0, 63.0, 62.0, 62.0, 62.0, 61.0, 62.0, 61.0], "avgHumidity": 62.6, "temperature": [23.12, 23.12, 23.37, 23.75, 23.75, 23.75, 23.87, 23.87, 23.87, 23.87], "avgTemperature": 23.634000000000004}, "4": {"pm2.5": [2.0, 2.0, 2.0, 2.0, 3.0, 3.0, 3.0, 3.0, 3.0, 3.0], "avgPm2.5": 2.6, "humidity": [61.0, 62.0, 63.0, 63.0, 63.0, 62.0, 62.0, 62.0, 62.0, 62.0], "avgHumidity": 62.2, "temperature": [23.87, 23.62, 23.5, 23.5, 23.62, 23.75, 24.0, 23.87, 23.75, 23.5], "avgTemperature": 23.698}, "5": {"pm2.5": [3.0, 3.0, 3.0, 3.0, 3.0, 3.0, 3.0, 4.0, 4.0, 4.0], "avgPm2.5": 3.3, "humidity": [63.0, 64.0, 64.0, 64.0, 64.0, 64.0, 64.0, 64.0, 64.0, 65.0], "avgHumidity": 64.0, "temperature": [23.37, 23.25, 23.12, 23.25, 23.12, 23.12, 23.12, 23.12, 23.12, 23.12], "avgTemperature": 23.171000000000003}, "6": {"pm2.5": [5.0, 4.0, 4.0, 3.0, 2.0, 2.0, 2.0, 2.0, 2.0, 2.0], "avgPm2.5": 2.8, "humidity": [65.0, 64.0, 63.0, 62.0, 62.0, 61.0, 61.0, 61.0, 61.0, 61.0], "avgHumidity": 62.1, "temperature": [23.12, 23.37, 23.37, 23.5, 23.5, 23.62, 23.75, 23.75, 23.75, 23.75], "avgTemperature": 23.548}, "7": {"pm2.5": [2.0, 2.0, 2.0, 1.0, 1.0, 2.0, 2.0, 2.0, 2.0], "avgPm2.5": 1.7777777777777777, "humidity": [61.0, 60.0, 61.0, 60.0, 60.0, 61.0, 61.0, 61.0, 60.0], "avgHumidity": 60.55555555555556, "temperature": [23.62, 23.75, 23.75, 23.75, 23.75, 23.75, 23.87, 23.87, 23.87], "avgTemperature": 23.775555555555556}, "8": {"pm2.5": [3.0, 3.0, 2.0, 2.0, 2.0, 1.0, 1.0, 1.0, 2.0, 1.0], "avgPm2.5": 1.8, "humidity": [61.0, 61.0, 60.0, 61.0, 60.0, 60.0, 60.0, 60.0, 60.0, 60.0], "avgHumidity": 60.3, "temperature": [23.87, 23.87, 23.75, 23.75, 23.62, 23.62, 23.62, 23.62, 23.62, 23.62], "avgTemperature": 23.696000000000005}, "9": {"pm2.5": [1.0, 1.0, 1.0, 1.0, 1.0, 0.0, 1.0, 1.0, 1.0, 1.0], "avgPm2.5": 0.9, "humidity": [60.0, 60.0, 60.0, 60.0, 60.0, 60.0, 59.0, 59.0, 60.0, 59.0], "avgHumidity": 59.7, "temperature": [23.62, 23.5, 23.5, 23.5, 23.37, 23.5, 23.5, 23.37, 23.37, 23.25], "avgTemperature": 23.448}, "10": {"pm2.5": [1.0, 1.0, 0.0, 1.0, 1.0, 1.0, 1.0, 1.0, 1.0, 1.0], "avgPm2.5": 0.9, "humidity": [60.0, 60.0, 60.0, 60.0, 60.0, 61.0, 61.0, 61.0, 61.0, 61.0], "avgHumidity": 60.5, "temperature": [23.12, 23.12, 23.0, 23.0, 22.87, 22.87, 23.0, 23.0, 22.87, 22.87], "avgTemperature": 22.972}, "11": {"pm2.5": [1.0, 1.0, 1.0, 1.0, 1.0, 1.0, 1.0, 1.0, 1.0], "avgPm2.5": 1.0, "humidity": [61.0, 61.0, 61.0, 61.0, 64.0, 65.0, 63.0, 62.0, 62.0], "avgHumidity": 62.22222222222222, "temperature": [22.75, 22.75, 22.62, 22.75, 22.75, 22.87, 22.75, 22.87, 22.87], "avgTemperature": 22.775555555555556}, "12": {"pm2.5": [1.0, 1.0, 1.0, 1.0, 1.0, 1.0, 1.0, 0.0, 1.0, 1.0], "avgPm2.5": 0.9, "humidity": [61.0, 66.0, 65.0, 63.0, 62.0, 61.0, 63.0, 65.0, 63.0, 62.0], "avgHumidity": 63.1, "temperature": [22.75, 22.75, 22.87, 22.87, 22.87, 22.87, 22.75, 22.87, 22.75, 22.75], "avgTemperature": 22.810000000000002}, "13": {"pm2.5": [1.0, 0.0, 1.0, 1.0, 0.0, 0.0, 0.0, 0.0, 0.0], "avgPm2.5": 0.3333333333333333, "humidity": [61.0, 65.0, 66.0, 63.0, 62.0, 61.0, 67.0, 65.0, 63.0], "avgHumidity": 63.666666666666664, "temperature": [22.75, 22.62, 22.87, 22.75, 22.75, 22.75, 22.87, 22.87, 22.75], "avgTemperature": 22.775555555555556}, "14": {"pm2.5": [1.0, 0.0, 0.0, 0.0, 0.0, 0.0, 0.0, 1.0, 0.0, 0.0], "avgPm2.5": 0.2, "humidity": [62.0, 61.0, 67.0, 65.0, 63.0, 63.0, 62.0, 67.0, 64.0, 63.0], "avgHumidity": 63.7, "temperature": [22.87, 22.75, 22.75, 22.75, 22.75, 22.75, 22.75, 22.87, 22.87, 22.75], "avgTemperature": 22.786}, "15": {"pm2.5": [0.0, 0.0, 0.0, 1.0, 0.0, 0.0, 0.0, 0.0, 0.0, 0.0], "avgPm2.5": 0.1, "humidity": [62.0, 67.0, 65.0, 63.0, 62.0, 66.0, 64.0, 62.0, 62.0, 67.0], "avgHumidity": 64.0, "temperature": [22.75, 22.62, 22.75, 22.87, 22.87, 22.87, 22.75, 22.75, 22.87, 23.0], "avgTemperature": 22.810000000000002}, "16": {"pm2.5": [], "avgPm2.5": 0, "humidity": [], "avgHumidity": 0, "temperature": [], "avgTemperature": 0}, "17": {"pm2.5": [], "avgPm2.5": 0, "humidity": [], "avgHumidity": 0, "temperature": [], "avgTemperature": 0}, "18": {"pm2.5": [], "avgPm2.5": 0, "humidity": [], "avgHumidity": 0, "temperature": [], "avgTemperature": 0}, "19": {"pm2.5": [], "avgPm2.5": 0, "humidity": [], "avgHumidity": 0, "temperature": [], "avgTemperature": 0}, "20": {"pm2.5": [], "avgPm2.5": 0, "humidity": [], "avgHumidity": 0, "temperature": [], "avgTemperature": 0}, "21": {"pm2.5": [], "avgPm2.5": 0, "humidity": [], "avgHumidity": 0, "temperature": [], "avgTemperature": 0}, "22": {"pm2.5": [0.0, 0.0, 0.0, 0.0, 0.0, 0.0, 0.0, 0.0, 0.0, 0.0], "avgPm2.5": 0.0, "humidity": [65.0, 63.0, 62.0, 68.0, 65.0, 63.0, 65.0, 65.0, 63.0, 63.0], "avgHumidity": 64.2, "temperature": [22.62, 22.62, 22.62, 22.75, 22.75, 22.75, 22.75, 22.75, 22.62, 22.62], "avgTemperature": 22.685000000000002}, "23": {"pm2.5": [0.0, 0.0, 0.0, 0.0, 0.0, 0.0, 0.0, 0.0, 0.0, 0.0], "avgPm2.5": 0.0, "humidity": [66.0, 66.0, 64.0, 62.0, 62.0, 67.0, 65.0, 63.0, 62.0, 67.0], "avgHumidity": 64.4, "temperature": [22.62, 22.75, 22.75, 22.75, 22.75, 22.75, 22.75, 22.75, 22.75, 22.75], "avgTemperature": 22.737000000000002}}, "2024-08-27": {"0": {"pm2.5": [0.0, 0.0, 0.0, 0.0, 0.0, 0.0, 0.0, 0.0, 0.0], "avgPm2.5": 0.0, "humidity": [65.0, 63.0, 63.0, 62.0, 62.0, 62.0, 61.0, 61.0, 61.0], "avgHumidity": 62.22222222222222, "temperature": [22.87, 22.75, 22.87, 23.0, 23.0, 23.12, 23.25, 23.25, 23.25], "avgTemperature": 23.040000000000003}, "1": {"pm2.5": [0.0, 0.0, 0.0, 0.0, 0.0, 1.0, 1.0, 0.0, 0.0, 1.0], "avgPm2.5": 0.3, "humidity": [61.0, 60.0, 60.0, 60.0, 60.0, 60.0, 60.0, 60.0, 60.0, 59.0], "avgHumidity": 60.0, "temperature": [23.37, 23.37, 23.37, 23.37, 23.37, 23.5, 23.5, 23.5, 23.37, 23.5], "avgTemperature": 23.422000000000004}, "2": {"pm2.5": [1.0, 1.0, 1.0, 1.0, 1.0, 1.0, 1.0, 1.0, 1.0, 1.0], "avgPm2.5": 1.0, "humidity": [60.0, 60.0, 60.0, 60.0, 60.0, 61.0, 61.0, 61.0, 61.0, 62.0], "avgHumidity": 60.6, "temperature": [23.5, 23.5, 23.5, 23.62, 23.5, 23.12, 23.0, 22.87, 22.75, 22.62], "avgTemperature": 23.198}, "3": {"pm2.5": [1.0, 1.0, 1.0, 1.0, 1.0, 1.0, 1.0, 1.0, 2.0, 2.0], "avgPm2.5": 1.2, "humidity": [62.0, 62.0, 62.0, 62.0, 62.0, 62.0, 62.0, 62.0, 62.0, 63.0], "avgHumidity": 62.1, "temperature": [22.62, 22.62, 22.62, 22.62, 22.62, 22.5, 22.62, 22.62, 22.62, 22.62], "avgTemperature": 22.608000000000004}, "4": {"pm2.5": [2.0, 2.0, 2.0, 3.0, 2.0, 2.0, 3.0, 3.0, 3.0, 3.0], "avgPm2.5": 2.5, "humidity": [62.0, 63.0, 63.0, 63.0, 63.0, 63.0, 63.0, 63.0, 63.0, 64.0], "avgHumidity": 63.0, "temperature": [22.62, 22.62, 22.62, 22.62, 22.62, 22.75, 22.75, 22.75, 22.75, 22.75], "avgTemperature": 22.685000000000002}, "5": {"pm2.5": [3.0, 3.0, 3.0, 2.0, 3.0, 3.0, 3.0, 3.0, 3.0, 3.0], "avgPm2.5": 2.9, "humidity": [63.0, 63.0, 63.0, 63.0, 64.0, 63.0, 63.0, 63.0, 63.0, 64.0], "avgHumidity": 63.2, "temperature": [22.87, 22.75, 22.87, 22.87, 22.87, 22.75, 22.87, 22.87, 22.87, 22.87], "avgTemperature": 22.846000000000004}, "6": {"pm2.5": [4.0, 4.0, 4.0, 4.0, 3.0, 3.0, 3.0, 3.0, 3.0], "avgPm2.5": 3.4444444444444446, "humidity": [64.0, 64.0, 64.0, 64.0, 64.0, 63.0, 63.0, 63.0, 63.0], "avgHumidity": 63.55555555555556, "temperature": [22.87, 23.0, 23.0, 23.0, 23.0, 22.87, 22.87, 22.87, 22.87], "avgTemperature": 22.92777777777778}, "7": {"pm2.5": [3.0, 3.0, 3.0, 2.0, 2.0, 2.0, 3.0, 3.0, 3.0, 3.0], "avgPm2.5": 2.7, "humidity": [63.0, 63.0, 63.0, 63.0, 63.0, 63.0, 64.0, 63.0, 63.0, 63.0], "avgHumidity": 63.1, "temperature": [23.0, 22.87, 23.0, 22.87, 22.87, 23.0, 22.87, 23.0, 23.0, 23.0], "avgTemperature": 22.948}, "8": {"pm2.5": [3.0, 3.0, 3.0, 2.0, 3.0, 3.0, 3.0, 3.0, 3.0, 3.0], "avgPm2.5": 2.9, "humidity": [63.0, 63.0, 63.0, 63.0, 64.0, 64.0, 64.0, 65.0, 64.0, 65.0], "avgHumidity": 63.8, "temperature": [23.0, 23.0, 23.0, 22.87, 22.75, 22.62, 22.5, 22.5, 22.5, 22.37], "avgTemperature": 22.711000000000002}, "9": {"pm2.5": [3.0, 3.0, 3.0, 3.0, 3.0, 3.0, 3.0, 3.0, 3.0, 3.0], "avgPm2.5": 3.0, "humidity": [65.0, 65.0, 65.0, 65.0, 65.0, 64.0, 65.0, 65.0, 64.0, 64.0], "avgHumidity": 64.7, "temperature": [22.37, 22.37, 22.25, 22.25, 22.25, 22.25, 22.25, 22.25, 22.25, 22.5], "avgTemperature": 22.299}, "10": {"pm2.5": [], "avgPm2.5": 0, "humidity": [], "avgHumidity": 0, "temperature": [], "avgTemperature": 0}, "11": {"pm2.5": [], "avgPm2.5": 0, "humidity": [], "avgHumidity": 0, "temperature": [], "avgTemperature": 0}, "12": {"pm2.5": [], "avgPm2.5": 0, "humidity": [], "avgHumidity": 0, "temperature": [], "avgTemperature": 0}, "13": {"pm2.5": [], "avgPm2.5": 0, "humidity": [], "avgHumidity": 0, "temperature": [], "avgTemperature": 0}, "14": {"pm2.5": [], "avgPm2.5": 0, "humidity": [], "avgHumidity": 0, "temperature": [], "avgTemperature": 0}, "15": {"pm2.5": [], "avgPm2.5": 0, "humidity": [], "avgHumidity": 0, "temperature": [], "avgTemperature": 0}, "16": {"pm2.5": [], "avgPm2.5": 0, "humidity": [], "avgHumidity": 0, "temperature": [], "avgTemperature": 0}, "17": {"pm2.5": [], "avgPm2.5": 0, "humidity": [], "avgHumidity": 0, "temperature": [], "avgTemperature": 0}, "18": {"pm2.5": [], "avgPm2.5": 0, "humidity": [], "avgHumidity": 0, "temperature": [], "avgTemperature": 0}, "19": {"pm2.5": [], "avgPm2.5": 0, "humidity": [], "avgHumidity": 0, "temperature": [], "avgTemperature": 0}, "20": {"pm2.5": [], "avgPm2.5": 0, "humidity": [], "avgHumidity": 0, "temperature": [], "avgTemperature": 0}, "21": {"pm2.5": [], "avgPm2.5": 0, "humidity": [], "avgHumidity": 0, "temperature": [], "avgTemperature": 0}, "22": {"pm2.5": [], "avgPm2.5": 0, "humidity": [], "avgHumidity": 0, "temperature": [], "avgTemperature": 0}, "23": {"pm2.5": [], "avgPm2.5": 0, "humidity": [], "avgHumidity": 0, "temperature": [], "avgTemperature": 0}}}}